CHANGELOG.txt
LICENSE.txt
MANIFEST.in
README.txt
__init__.py
gcs_read_file.py
get_connection.py
main.py
parse_input_config.py
process_metrics.py
read_dataset.py
setup.py
test.py
write_metrics.py
pydeequ_module.egg-info/PKG-INFO
pydeequ_module.egg-info/SOURCES.txt
pydeequ_module.egg-info/dependency_links.txt
pydeequ_module.egg-info/top_level.txt