Metadata-Version: 2.1
Name: pydeequ-module
Version: 0.0.1
Summary: data assertion pydeequ module
Home-page: UNKNOWN
Author: IIG
Author-email: 
License: MIT
Keywords: pydeequ-data-assertion
Platform: UNKNOWN
Classifier: Development Status :: 5 - Production/Stable
Classifier: Intended Audience :: Developers
Classifier: Operating System :: Microsoft :: Windows :: Windows 10
Classifier: License :: OSI Approved :: MIT License
Classifier: Programming Language :: Python :: 3
License-File: LICENSE.txt
